pyuu/usys/CONST.py
pyuu/usys/__init__.py
pyuu/usys/common.py
pyuu/usys/core.py
pyuu/usys/tool.py
pyuu/usys/util.py
pyuu/usys/pm/__init__.py
pyuu/usys/service/PkgMngrService.py
pyuu/usys/service/PkgService.py
pyuu/usys/service/__init__.py
pyuu/usys/service/common.py
pyuu.usys-0.0.2.dist-info/METADATA
pyuu.usys-0.0.2.dist-info/WHEEL
pyuu.usys-0.0.2.dist-info/top_level.txt
pyuu.usys-0.0.2.dist-info/RECORD
