Metadata-Version: 2.1
Name: pyuu.usys
Version: 0.0.2
Summary: usys
Home-page: https://github.com/happyxianyu/uu
Author: happyxianyu
Author-email: happyxianyu623@outlook.com
License: Apache License 2.0
Requires-Python: >=3.8
Requires-Dist: sqlalchemy
Requires-Dist: pyuu.trivial
Requires-Dist: pyuu.uimport
Requires-Dist: pyuu.env
Requires-Dist: pyuu.project
Requires-Dist: pyuu.path
